<groups><group guid="{00000000-0000-0000-0000-000000000000}" enable="True"><Name>default</Name><Comments>default folder (root)</Comments></group><group guid="{FFFFFFFF-FFFF-FFFF-FFFF-FFFFFFFFFFFF}" enable="True"><Name>hidden</Name><Comments>This folder contains shared source items that have not been made explicitly visible in this deployment share.</Comments></group><group guid="{e1645857-8cab-4533-a4cd-f84fc6c4b87a}" enable="True"><Name>Windows 10 20H2</Name><Comments></Comments><CreatedTime>5/01/2021 9:29:33 PM</CreatedTime><CreatedBy>ad\sb</CreatedBy><LastModifiedTime>5/01/2021 9:30:17 PM</LastModifiedTime><LastModifiedBy>ad\sb</LastModifiedBy><Member>{112e6963-062f-4e93-a069-16f110220a7a}</Member><Member>{cdbed577-f951-40f9-b4fe-52c995f48348}</Member><Member>{97954886-d0d9-48d2-9320-d7f2d79fdb60}</Member></group></groups>